design.sv
// Code your design here
// Code your design here
module uart_tx(
  input clk,
  input rst,
  input tx_start,
  input [7:0]tx_data,
  output reg tx_out,tx_done
);
  parameter baud_rate=9600;
  parameter clock_frequency=50000000;
  localparam cycles_per_bit=clock_frequency/baud_rate;
  localparam idle=0,start=1,data=2,stop=3;
  reg [1:0]state;
  reg [15:0]bit_count;
  reg [3:0]bit_index;
  reg [7:0]data_reg;
  always @(posedge clk or posedge rst) begin
    if(rst) begin
      state<=idle;
      tx_out<=1'b1;
      tx_done<=1'b0;
    end
  else begin 
    case(state)
      idle: begin
        tx_out<=1'b1;
        tx_done<=1'b0;
        if(tx_start)begin
          state<=start;
          data_reg<=tx_data;
        bit_count<=0;
        end
      end
        start:begin 
          tx_out<=1'b0; 
          if(bit_count==cycles_per_bit-1)begin
            state<=data;
            bit_count<=0;
            bit_index<=0;
          end
          else 
            bit_count<=bit_count+1;        
        end
      data:begin 
        tx_out<=data_reg[bit_index];
        if(bit_count==cycles_per_bit-1) begin
          bit_count<=0;
          if(bit_index==7) 
            state<=stop;
          else
            bit_index<=bit_index+1;
        end
         else
           bit_count<=bit_count+1;
        end
      stop:begin
        tx_out<=1;
        if(bit_count==cycles_per_bit-1) begin 
        state<=idle;
          tx_done<=1'b1;
        end
          else 
          bit_count<=bit_count+1;
      end
    endcase
      end
     
      end
      endmodule
 




// Code your design here
module uart_rx(
input rx_in,clk,rst,
  output reg [7:0]rx_out,
  output reg rx_done
);
  parameter baud_rate=9600;
  parameter clock_freq=50_000_000;
  localparam cycles_per_bit=clock_freq/baud_rate;
  localparam idle=0,start=1,data=2,stop=3;
  reg [1:0] state;
  reg [15:0] bit_count;
  reg [2:0]bit_index;
  always @(posedge clk) begin 
    if(rst) begin 
      state<=idle;
      rx_done<=1'b0;
      bit_index<=0;
      bit_count<=0;
    end
    else begin 
      case(state)
        idle:begin 
          if(!rx_in)
            state<=start;
          bit_count<=0;
          rx_done<=1'b0;
        end
        start:begin 
          if(bit_count==(cycles_per_bit/2)) begin 
            if(!rx_in) begin 
              state<=data;
            bit_count<=0;
            bit_index<=0;
              rx_done<=1'b0;
            end
            else 
              state<=idle;
          end
            else 
              bit_count<=bit_count+1;
        end
        data:begin  
          if(bit_count==cycles_per_bit-1) begin 
          rx_out[bit_index]<=rx_in;
            bit_count<=0;
            if(bit_index==7) 
              state<=stop;
            else 
              bit_index<=bit_index+1;
          end
            else
              bit_count<=bit_count+1;
        end
          stop:begin
            if(bit_count==cycles_per_bit-1) begin
              bit_count<=0;
              state<=idle;
              rx_done<=1'b1;
            end
            else 
              bit_count<=bit_count+1;
          end
        default:state<=idle;
      endcase 
    end
  end
        endmodule




// `include "design.sv"

module uart_top(
    input clk,
    input rst,
    input tx_start,
    input [7:0] tx_data,
    output tx_out,
    output tx_done,
    output [7:0] rx_out,
    output rx_done
);
  wire w1;
    
    // Instantiate UART transmitter
    uart_tx tx_inst(
        .clk(clk),
        .rst(rst),
        .tx_start(tx_start),
        .tx_data(tx_data),
      .tx_out(w1),
        .tx_done(tx_done)
    );
    
    // Instantiate UART receiver
    uart_rx rx_inst(
        .clk(clk),
        .rst(rst),
      .rx_in(w1),
        .rx_out(rx_out),
        .rx_done(rx_done)
    );
    
endmodule

testbench.sv
module tb;
  parameter baud_rate=9600;
  parameter bit_period=1000000000/baud_rate;
  reg clk,rst,tx_start,tx_done;
  reg [7:0]tx_data;
  wire tx_out;
  wire [7:0]rx_out;
  wire rx_in,rx_done;
  uart_top uut(.clk(clk),.rst(rst),.tx_start(tx_start),.tx_data(tx_data),.tx_out(tx_out),.tx_done(tx_done),.rx_out(rx_out),.rx_done(rx_done));
  initial begin 
    clk=0;
    forever #10 clk=~clk;
  end
  initial begin
  
    rst=1;
    tx_start=0;
    #30
    rst=0;
    #10
    tx_start=1;
    tx_data=8'h55;
    #20
    tx_start=0;
    wait(rx_done==1);
    #20
    if(tx_data==rx_out) begin
      $display("success:done=%b,tx_data=%h,received data=%h",rx_done,tx_data,rx_out);

    $finish;
    end
    else 
      $display("Transmission failed");
  end
  initial begin
      $dumpfile("uart_rx_tb.vcd");
    $dumpvars(1,tb.rx_out);
    $dumpvars(1,tb.rx_done);
    $dumpvars(1,tb.tx_data);
    

  end
endmodule

uart_rx_tb.vcd
$date
	Wed Jun  4 13:35:02 2025
$end
$version
	Icarus Verilog
$end
$timescale
	1s
$end
$scope module tb $end
$var wire 8 ! rx_out [7:0] $end
$upscope $end
$scope module tb $end
$var wire 1 " rx_done $end
$upscope $end
$scope module tb $end
$var reg 8 # tx_data [7:0] $end
$upscope $end
$enddefinitions $end
$comment Show the parameter values. $end
$dumpall
$end
#0
$dumpvars
bx #
x"
bx !
$end
#10
0"
#40
b1010101 #
#156350
bx1 !
#260510
bx01 !
#364670
bx101 !
#468830
bx0101 !
#572990
bx10101 !
#677150
bx010101 !
#781310
bx1010101 !
#885470
b1010101 !
#989630
1"
#989650
0"
